timenotes/__init__.py
timenotes/timenotes.py
timenotes-1.0.dist-info/LICENSE
timenotes-1.0.dist-info/METADATA
timenotes-1.0.dist-info/WHEEL
timenotes-1.0.dist-info/top_level.txt
timenotes-1.0.dist-info/RECORD
