Metadata-Version: 2.1
Name: timenotes
Version: 1.0
Summary: easy-use tool for record running time
Home-page: https://github.com/Hamlet-Fansion/timenotes
Author: Fan Peilin
Author-email: fanpeilin123@126.com
License: MIT
Platform: UNKNOWN
Classifier: Topic :: Software Development :: Libraries :: Python Modules
Classifier: Programming Language :: Python
Classifier: Programming Language :: Python :: 3
Classifier: Programming Language :: Python :: 3.5
Classifier: Programming Language :: Python :: 3.6
Classifier: Programming Language :: Python :: 3.7
Classifier: Programming Language :: Python :: 3.8
Classifier: Programming Language :: Python :: Implementation :: CPython
